MANIFEST.in
README.rst
icon.png
requirements.txt
setup.py
./jirachi/__init__.py
./jirachi/__main__.py
./jirachi/__meta__.py
./jirachi/utils.py
./jirachi/core/__init__.py
./jirachi/core/decorators.py
./jirachi/core/types.py
./jirachi/core/wsgi.py
./jirachi/io/__init__.py
./jirachi/io/abstract.py
./jirachi/io/mongodb/__init__.py
./jirachi/io/mongodb/monitor.py
./jirachi/io/postgres/__init__.py
./jirachi/io/postgres/monitor.py
./jirachi/io/postgres/queryset.py
./jirachi/io/postgres/types.py
./jirachi/io/postgres/utils.py
./jirachi/io/remote/__init__.py
./jirachi/io/remote/monitor.py
./jirachi/io/requests/__init__.py
./jirachi/io/requests/monitor.py
./jirachi/io/scheduler/__init__.py
./jirachi/io/scheduler/monitor.py
./tests/core/__init__.py
./tests/core/test_multi_app.py
./tests/io/__init__.py
./tests/io/test_requests.py
./tests/io/test_scheduler.py
./tests/io/remote/__init__.py
./tests/io/remote/test_remote_wsgi.py
jirachi.egg-info/PKG-INFO
jirachi.egg-info/SOURCES.txt
jirachi.egg-info/dependency_links.txt
jirachi.egg-info/entry_points.txt
jirachi.egg-info/requires.txt
jirachi.egg-info/top_level.txt