Metadata-Version: 1.1
Name: jirachi
Version: 0.1.2.14
Summary: jirachi is an actor model based IO framework
Home-page: UNKNOWN
Author: ryankung
Author-email: ryankung@ieee.org
License: MIT
Platform: any
Classifier: Intended Audience :: Developers
Classifier: Programming Language :: Python
Classifier: Topic :: Software Development :: Libraries :: Python Modules
